paraplot/__init__.py
paraplot/config.json.works
paraplot/paraplot.py
paraplot/py.typed
paraplot-0.1.0.dist-info/LICENSE
paraplot-0.1.0.dist-info/WHEEL
paraplot-0.1.0.dist-info/METADATA
paraplot-0.1.0.dist-info/RECORD
