Metadata-Version: 2.1
Name: paraplot
Version: 0.1.0
Summary: Parameter retrieval and plotting
Home-page: https://github.com/cruisen/paraplot
License: MIT
Author: Nikolai von Krusenstiern
Requires-Python: >=3.7,<4.0
Classifier: Development Status :: 3 - Alpha
Classifier: Intended Audience :: Developers
Classifier: License :: OSI Approved :: MIT License
Classifier: Operating System :: OS Independent
Classifier: Programming Language :: Python :: 3
Classifier: Programming Language :: Python :: 3.7
Classifier: Programming Language :: Python :: 3.8
Classifier: Topic :: Software Development :: Libraries :: Python Modules
Requires-Dist: IPython (>=7.17.0,<8.0.0)
Requires-Dist: flask (>=1.1.2,<2.0.0)
Requires-Dist: json_minify (>=0.3.0,<0.4.0)
Requires-Dist: matplotlib (>=3.3.0,<4.0.0)
Requires-Dist: pandas (>=1.1.0,<2.0.0)
Requires-Dist: requests (>=2.24.0,<3.0.0)
Requires-Dist: requests_cache (>=0.5.2,<0.6.0)
Project-URL: Repository, https://github.com/cruisen/paraplot
